source_trello/__init__.py
source_trello/components.py
source_trello/manifest.yaml
source_trello/run.py
source_trello/schemas/actions.json
source_trello/schemas/boards.json
source_trello/schemas/cards.json
source_trello/schemas/checklists.json
source_trello/schemas/lists.json
source_trello/schemas/organizations.json
source_trello/schemas/users.json
source_trello/source.py
airbyte_source_trello-1.1.0.dist-info/METADATA
airbyte_source_trello-1.1.0.dist-info/WHEEL
airbyte_source_trello-1.1.0.dist-info/entry_points.txt
airbyte_source_trello-1.1.0.dist-info/RECORD
